odoo8_addon_l10n_ar_tax_reports-8.0.1.0.0-py2.7-nspkg.pth
odoo_addons/l10n_ar_tax_reports/.gitignore
odoo_addons/l10n_ar_tax_reports/tax_report_config_view.xml
odoo_addons/l10n_ar_tax_reports/__openerp__.py
odoo_addons/l10n_ar_tax_reports/tax_report.xml
odoo_addons/l10n_ar_tax_reports/__init__.py
odoo_addons/l10n_ar_tax_reports/tax_report_config.py
odoo_addons/l10n_ar_tax_reports/security/ir.model.access.csv
odoo_addons/l10n_ar_tax_reports/report/parser.py
odoo_addons/l10n_ar_tax_reports/report/template.ods
odoo_addons/l10n_ar_tax_reports/wizard/account_tax_subjournal.py
odoo_addons/l10n_ar_tax_reports/wizard/__init__.py
odoo_addons/l10n_ar_tax_reports/wizard/account_tax_subjournal_view.xml
odoo8_addon_l10n_ar_tax_reports-8.0.1.0.0.dist-info/top_level.txt
odoo8_addon_l10n_ar_tax_reports-8.0.1.0.0.dist-info/WHEEL
odoo8_addon_l10n_ar_tax_reports-8.0.1.0.0.dist-info/RECORD
odoo8_addon_l10n_ar_tax_reports-8.0.1.0.0.dist-info/metadata.json
odoo8_addon_l10n_ar_tax_reports-8.0.1.0.0.dist-info/DESCRIPTION.rst
odoo8_addon_l10n_ar_tax_reports-8.0.1.0.0.dist-info/METADATA
odoo8_addon_l10n_ar_tax_reports-8.0.1.0.0.dist-info/namespace_packages.txt
