Metadata-Version: 2.0
Name: odoo8-addon-l10n-ar-tax-reports
Version: 8.0.1.0.0
Summary: Tax Reports for Argentina
Home-page: http://e-mips.com.ar
Author: UNKNOWN
Author-email: UNKNOWN
License: GPL-3
Platform: UNKNOWN
Requires-Dist: odoo (<9.0a,>=8.0a)
Requires-Dist: odoo8-addon-l10n-ar-account-payment
Requires-Dist: odoo8-addon-l10n-ar-chart-of-account
Requires-Dist: odoo8-addon-l10n-ar-perceptions-basic
Requires-Dist: odoo8-addon-l10n-ar-retentions-basic
Classifier: Programming Language :: Python :: 2.7
Classifier: Framework :: Odoo
Classifier: License :: OSI Approved :: GNU General Public License v3 (GPLv3)
